[
  {
    "work_date": "2026-07-11",
    "brand": "일룸",
    "worker": "[주간]김태운",
    "worker_display": "김태운",
    "rows": 2,
    "hours": 1.874167,
    "basic_qty_normal": 41.0,
    "basic_amt_normal": 7351700.0,
    "basic_qty_return": 0.0,
    "basic_amt_return": 0.0,
    "basic_qty_cut": 0.0,
    "basic_amt_cut": 0.0,
    "basic_pallets": 2,
    "detail_qty_normal": 0.0,
    "detail_amt_normal": 0.0,
    "detail_qty_return": 0.0,
    "detail_amt_return": 0.0,
    "detail_qty_certify": 0.0,
    "detail_amt_certify": 0.0,
    "detail_qty_reentry": 0.0,
    "detail_amt_reentry": 0.0,
    "detail_qty_inspect": 41.0,
    "detail_amt_inspect": 7351700.0,
    "detail_qty_cut": 0.0,
    "detail_amt_cut": 0.0,
    "detail_pallets": 2,
    "qty_total": 41.0,
    "amt_total": 7351700.0
  },
  {
    "work_date": "2026-07-11",
    "brand": "일룸",
    "worker": "[주간]김혜성",
    "worker_display": "김혜성",
    "rows": 3,
    "hours": 0.011389,
    "basic_qty_normal": 0.0,
    "basic_amt_normal": 0.0,
    "basic_qty_return": 0.0,
    "basic_amt_return": 0.0,
    "basic_qty_cut": 3.0,
    "basic_amt_cut": 250900.0,
    "basic_pallets": 0,
    "detail_qty_normal": 0.0,
    "detail_amt_normal": 0.0,
    "detail_qty_return": 0.0,
    "detail_amt_return": 0.0,
    "detail_qty_certify": 0.0,
    "detail_amt_certify": 0.0,
    "detail_qty_reentry": 0.0,
    "detail_amt_reentry": 0.0,
    "detail_qty_inspect": 0.0,
    "detail_amt_inspect": 0.0,
    "detail_qty_cut": 3.0,
    "detail_amt_cut": 250900.0,
    "detail_pallets": 0,
    "qty_total": 3.0,
    "amt_total": 250900.0
  },
  {
    "work_date": "2026-07-11",
    "brand": "일룸",
    "worker": "[주간]어건",
    "worker_display": "어건",
    "rows": 74,
    "hours": 5.849167,
    "basic_qty_normal": 101.0,
    "basic_amt_normal": 5538060.0,
    "basic_qty_return": 0.0,
    "basic_amt_return": 0.0,
    "basic_qty_cut": 0.0,
    "basic_amt_cut": 0.0,
    "basic_pallets": 74,
    "detail_qty_normal": 0.0,
    "detail_amt_normal": 0.0,
    "detail_qty_return": 0.0,
    "detail_amt_return": 0.0,
    "detail_qty_certify": 88.0,
    "detail_amt_certify": 3769360.0,
    "detail_qty_reentry": 11.0,
    "detail_amt_reentry": 1651240.0,
    "detail_qty_inspect": 2.0,
    "detail_amt_inspect": 117460.0,
    "detail_qty_cut": 0.0,
    "detail_amt_cut": 0.0,
    "detail_pallets": 74,
    "qty_total": 101.0,
    "amt_total": 5538060.0
  },
  {
    "work_date": "2026-07-11",
    "brand": "일룸",
    "worker": "[주간]이봉진",
    "worker_display": "이봉진",
    "rows": 6,
    "hours": 0.008611,
    "basic_qty_normal": 4.0,
    "basic_amt_normal": 52400.0,
    "basic_qty_return": 0.0,
    "basic_amt_return": 0.0,
    "basic_qty_cut": 6.0,
    "basic_amt_cut": 442800.0,
    "basic_pallets": 1,
    "detail_qty_normal": 4.0,
    "detail_amt_normal": 52400.0,
    "detail_qty_return": 0.0,
    "detail_amt_return": 0.0,
    "detail_qty_certify": 0.0,
    "detail_amt_certify": 0.0,
    "detail_qty_reentry": 0.0,
    "detail_amt_reentry": 0.0,
    "detail_qty_inspect": 0.0,
    "detail_amt_inspect": 0.0,
    "detail_qty_cut": 6.0,
    "detail_amt_cut": 442800.0,
    "detail_pallets": 1,
    "qty_total": 10.0,
    "amt_total": 495200.0
  },
  {
    "work_date": "2026-07-11",
    "brand": "일룸",
    "worker": "[주간]정민규",
    "worker_display": "정민규",
    "rows": 59,
    "hours": 2.566667,
    "basic_qty_normal": 0.0,
    "basic_amt_normal": 0.0,
    "basic_qty_return": 73.0,
    "basic_amt_return": 4031400.0,
    "basic_qty_cut": 0.0,
    "basic_amt_cut": 0.0,
    "basic_pallets": 59,
    "detail_qty_normal": 0.0,
    "detail_amt_normal": 0.0,
    "detail_qty_return": 73.0,
    "detail_amt_return": 4031400.0,
    "detail_qty_certify": 0.0,
    "detail_amt_certify": 0.0,
    "detail_qty_reentry": 0.0,
    "detail_amt_reentry": 0.0,
    "detail_qty_inspect": 0.0,
    "detail_amt_inspect": 0.0,
    "detail_qty_cut": 0.0,
    "detail_amt_cut": 0.0,
    "detail_pallets": 59,
    "qty_total": 73.0,
    "amt_total": 4031400.0
  },
  {
    "work_date": "2026-07-11",
    "brand": "일룸",
    "worker": "서형준",
    "worker_display": "서형준",
    "rows": 16,
    "hours": 0.013333,
    "basic_qty_normal": 0.0,
    "basic_amt_normal": 0.0,
    "basic_qty_return": 17.0,
    "basic_amt_return": 329600.0,
    "basic_qty_cut": 0.0,
    "basic_amt_cut": 0.0,
    "basic_pallets": 16,
    "detail_qty_normal": 0.0,
    "detail_amt_normal": 0.0,
    "detail_qty_return": 17.0,
    "detail_amt_return": 329600.0,
    "detail_qty_certify": 0.0,
    "detail_amt_certify": 0.0,
    "detail_qty_reentry": 0.0,
    "detail_amt_reentry": 0.0,
    "detail_qty_inspect": 0.0,
    "detail_amt_inspect": 0.0,
    "detail_qty_cut": 0.0,
    "detail_amt_cut": 0.0,
    "detail_pallets": 16,
    "qty_total": 17.0,
    "amt_total": 329600.0
  },
  {
    "work_date": "2026-07-11",
    "brand": "데스커",
    "worker": "[주간]김규태",
    "worker_display": "김규태",
    "rows": 42,
    "hours": 0.171944,
    "basic_qty_normal": 0.0,
    "basic_amt_normal": 0.0,
    "basic_qty_return": 44.0,
    "basic_amt_return": 1033180.0,
    "basic_qty_cut": 0.0,
    "basic_amt_cut": 0.0,
    "basic_pallets": 42,
    "detail_qty_normal": 0.0,
    "detail_amt_normal": 0.0,
    "detail_qty_return": 44.0,
    "detail_amt_return": 1033180.0,
    "detail_qty_certify": 0.0,
    "detail_amt_certify": 0.0,
    "detail_qty_reentry": 0.0,
    "detail_amt_reentry": 0.0,
    "detail_qty_inspect": 0.0,
    "detail_amt_inspect": 0.0,
    "detail_qty_cut": 0.0,
    "detail_amt_cut": 0.0,
    "detail_pallets": 42,
    "qty_total": 44.0,
    "amt_total": 1033180.0
  },
  {
    "work_date": "2026-07-11",
    "brand": "데스커",
    "worker": "[주간]조진형",
    "worker_display": "조진형",
    "rows": 39,
    "hours": 0.721667,
    "basic_qty_normal": 0.0,
    "basic_amt_normal": 0.0,
    "basic_qty_return": 40.0,
    "basic_amt_return": 2347000.0,
    "basic_qty_cut": 0.0,
    "basic_amt_cut": 0.0,
    "basic_pallets": 39,
    "detail_qty_normal": 0.0,
    "detail_amt_normal": 0.0,
    "detail_qty_return": 40.0,
    "detail_amt_return": 2347000.0,
    "detail_qty_certify": 0.0,
    "detail_amt_certify": 0.0,
    "detail_qty_reentry": 0.0,
    "detail_amt_reentry": 0.0,
    "detail_qty_inspect": 0.0,
    "detail_amt_inspect": 0.0,
    "detail_qty_cut": 0.0,
    "detail_amt_cut": 0.0,
    "detail_pallets": 39,
    "qty_total": 40.0,
    "amt_total": 2347000.0
  },
  {
    "work_date": "2026-07-11",
    "brand": "데스커",
    "worker": "[주간]최우성",
    "worker_display": "최우성",
    "rows": 17,
    "hours": 0.071944,
    "basic_qty_normal": 0.0,
    "basic_amt_normal": 0.0,
    "basic_qty_return": 18.0,
    "basic_amt_return": 728400.0,
    "basic_qty_cut": 0.0,
    "basic_amt_cut": 0.0,
    "basic_pallets": 17,
    "detail_qty_normal": 0.0,
    "detail_amt_normal": 0.0,
    "detail_qty_return": 18.0,
    "detail_amt_return": 728400.0,
    "detail_qty_certify": 0.0,
    "detail_amt_certify": 0.0,
    "detail_qty_reentry": 0.0,
    "detail_amt_reentry": 0.0,
    "detail_qty_inspect": 0.0,
    "detail_amt_inspect": 0.0,
    "detail_qty_cut": 0.0,
    "detail_amt_cut": 0.0,
    "detail_pallets": 17,
    "qty_total": 18.0,
    "amt_total": 728400.0
  },
  {
    "work_date": "2026-07-11",
    "brand": "퍼시스",
    "worker": "김진태",
    "worker_display": "김진태",
    "rows": 4,
    "hours": 0.120278,
    "basic_qty_normal": 105.0,
    "basic_amt_normal": 22110000.0,
    "basic_qty_return": 0.0,
    "basic_amt_return": 0.0,
    "basic_qty_cut": 0.0,
    "basic_amt_cut": 0.0,
    "basic_pallets": 4,
    "detail_qty_normal": 105.0,
    "detail_amt_normal": 22110000.0,
    "detail_qty_return": 0.0,
    "detail_amt_return": 0.0,
    "detail_qty_certify": 0.0,
    "detail_amt_certify": 0.0,
    "detail_qty_reentry": 0.0,
    "detail_amt_reentry": 0.0,
    "detail_qty_inspect": 0.0,
    "detail_amt_inspect": 0.0,
    "detail_qty_cut": 0.0,
    "detail_amt_cut": 0.0,
    "detail_pallets": 4,
    "qty_total": 105.0,
    "amt_total": 22110000.0
  },
  {
    "work_date": "2026-07-11",
    "brand": "퍼시스",
    "worker": "김태우",
    "worker_display": "김태우",
    "rows": 6,
    "hours": 2.233056,
    "basic_qty_normal": 120.0,
    "basic_amt_normal": 12024000.0,
    "basic_qty_return": 0.0,
    "basic_amt_return": 0.0,
    "basic_qty_cut": 0.0,
    "basic_amt_cut": 0.0,
    "basic_pallets": 6,
    "detail_qty_normal": 120.0,
    "detail_amt_normal": 12024000.0,
    "detail_qty_return": 0.0,
    "detail_amt_return": 0.0,
    "detail_qty_certify": 0.0,
    "detail_amt_certify": 0.0,
    "detail_qty_reentry": 0.0,
    "detail_amt_reentry": 0.0,
    "detail_qty_inspect": 0.0,
    "detail_amt_inspect": 0.0,
    "detail_qty_cut": 0.0,
    "detail_amt_cut": 0.0,
    "detail_pallets": 6,
    "qty_total": 120.0,
    "amt_total": 12024000.0
  },
  {
    "work_date": "2026-07-11",
    "brand": "퍼시스",
    "worker": "김혁",
    "worker_display": "김혁",
    "rows": 38,
    "hours": 4.265556,
    "basic_qty_normal": 509.0,
    "basic_amt_normal": 55217000.0,
    "basic_qty_return": 0.0,
    "basic_amt_return": 0.0,
    "basic_qty_cut": 88.0,
    "basic_amt_cut": 13168000.0,
    "basic_pallets": 25,
    "detail_qty_normal": 509.0,
    "detail_amt_normal": 55217000.0,
    "detail_qty_return": 0.0,
    "detail_amt_return": 0.0,
    "detail_qty_certify": 0.0,
    "detail_amt_certify": 0.0,
    "detail_qty_reentry": 0.0,
    "detail_amt_reentry": 0.0,
    "detail_qty_inspect": 0.0,
    "detail_amt_inspect": 0.0,
    "detail_qty_cut": 88.0,
    "detail_amt_cut": 13168000.0,
    "detail_pallets": 25,
    "qty_total": 597.0,
    "amt_total": 68385000.0
  },
  {
    "work_date": "2026-07-11",
    "brand": "퍼시스",
    "worker": "임길재",
    "worker_display": "임길재",
    "rows": 5,
    "hours": 0.450278,
    "basic_qty_normal": 150.0,
    "basic_amt_normal": 12690000.0,
    "basic_qty_return": 0.0,
    "basic_amt_return": 0.0,
    "basic_qty_cut": 0.0,
    "basic_amt_cut": 0.0,
    "basic_pallets": 5,
    "detail_qty_normal": 150.0,
    "detail_amt_normal": 12690000.0,
    "detail_qty_return": 0.0,
    "detail_amt_return": 0.0,
    "detail_qty_certify": 0.0,
    "detail_amt_certify": 0.0,
    "detail_qty_reentry": 0.0,
    "detail_amt_reentry": 0.0,
    "detail_qty_inspect": 0.0,
    "detail_amt_inspect": 0.0,
    "detail_qty_cut": 0.0,
    "detail_amt_cut": 0.0,
    "detail_pallets": 5,
    "qty_total": 150.0,
    "amt_total": 12690000.0
  },
  {
    "work_date": "2026-07-11",
    "brand": "퍼시스",
    "worker": "홍석호",
    "worker_display": "홍석호",
    "rows": 29,
    "hours": 0.836111,
    "basic_qty_normal": 168.0,
    "basic_amt_normal": 20160000.0,
    "basic_qty_return": 0.0,
    "basic_amt_return": 0.0,
    "basic_qty_cut": 81.0,
    "basic_amt_cut": 11646000.0,
    "basic_pallets": 14,
    "detail_qty_normal": 168.0,
    "detail_amt_normal": 20160000.0,
    "detail_qty_return": 0.0,
    "detail_amt_return": 0.0,
    "detail_qty_certify": 0.0,
    "detail_amt_certify": 0.0,
    "detail_qty_reentry": 0.0,
    "detail_amt_reentry": 0.0,
    "detail_qty_inspect": 0.0,
    "detail_amt_inspect": 0.0,
    "detail_qty_cut": 81.0,
    "detail_amt_cut": 11646000.0,
    "detail_pallets": 14,
    "qty_total": 249.0,
    "amt_total": 31806000.0
  },
  {
    "work_date": "2026-07-11",
    "brand": "3PL",
    "worker": "고윤석",
    "worker_display": "고윤석",
    "rows": 2,
    "hours": 0.002222,
    "basic_qty_normal": 0.0,
    "basic_amt_normal": 0.0,
    "basic_qty_return": 2.0,
    "basic_amt_return": 1084455.0,
    "basic_qty_cut": 0.0,
    "basic_amt_cut": 0.0,
    "basic_pallets": 2,
    "detail_qty_normal": 0.0,
    "detail_amt_normal": 0.0,
    "detail_qty_return": 2.0,
    "detail_amt_return": 1084455.0,
    "detail_qty_certify": 0.0,
    "detail_amt_certify": 0.0,
    "detail_qty_reentry": 0.0,
    "detail_amt_reentry": 0.0,
    "detail_qty_inspect": 0.0,
    "detail_amt_inspect": 0.0,
    "detail_qty_cut": 0.0,
    "detail_amt_cut": 0.0,
    "detail_pallets": 2,
    "qty_total": 2.0,
    "amt_total": 1084455.0
  },
  {
    "work_date": "2026-07-11",
    "brand": "3PL",
    "worker": "김석현",
    "worker_display": "김석현",
    "rows": 2,
    "hours": 0.295833,
    "basic_qty_normal": 7.0,
    "basic_amt_normal": 4657184.0,
    "basic_qty_return": 0.0,
    "basic_amt_return": 0.0,
    "basic_qty_cut": 0.0,
    "basic_amt_cut": 0.0,
    "basic_pallets": 2,
    "detail_qty_normal": 7.0,
    "detail_amt_normal": 4657184.0,
    "detail_qty_return": 0.0,
    "detail_amt_return": 0.0,
    "detail_qty_certify": 0.0,
    "detail_amt_certify": 0.0,
    "detail_qty_reentry": 0.0,
    "detail_amt_reentry": 0.0,
    "detail_qty_inspect": 0.0,
    "detail_amt_inspect": 0.0,
    "detail_qty_cut": 0.0,
    "detail_amt_cut": 0.0,
    "detail_pallets": 2,
    "qty_total": 7.0,
    "amt_total": 4657184.0
  },
  {
    "work_date": "2026-07-11",
    "brand": "3PL",
    "worker": "박성범",
    "worker_display": "박성범",
    "rows": 25,
    "hours": 3.759444,
    "basic_qty_normal": 135.0,
    "basic_amt_normal": 32400000.0,
    "basic_qty_return": 16.0,
    "basic_amt_return": 1493000.0,
    "basic_qty_cut": 0.0,
    "basic_amt_cut": 0.0,
    "basic_pallets": 25,
    "detail_qty_normal": 135.0,
    "detail_amt_normal": 32400000.0,
    "detail_qty_return": 16.0,
    "detail_amt_return": 1493000.0,
    "detail_qty_certify": 0.0,
    "detail_amt_certify": 0.0,
    "detail_qty_reentry": 0.0,
    "detail_amt_reentry": 0.0,
    "detail_qty_inspect": 0.0,
    "detail_amt_inspect": 0.0,
    "detail_qty_cut": 0.0,
    "detail_amt_cut": 0.0,
    "detail_pallets": 25,
    "qty_total": 151.0,
    "amt_total": 33893000.0
  },
  {
    "work_date": "2026-07-11",
    "brand": "3PL",
    "worker": "성준혁",
    "worker_display": "성준혁",
    "rows": 4,
    "hours": 0.249167,
    "basic_qty_normal": 24.0,
    "basic_amt_normal": 16341828.0,
    "basic_qty_return": 0.0,
    "basic_amt_return": 0.0,
    "basic_qty_cut": 0.0,
    "basic_amt_cut": 0.0,
    "basic_pallets": 4,
    "detail_qty_normal": 24.0,
    "detail_amt_normal": 16341828.0,
    "detail_qty_return": 0.0,
    "detail_amt_return": 0.0,
    "detail_qty_certify": 0.0,
    "detail_amt_certify": 0.0,
    "detail_qty_reentry": 0.0,
    "detail_amt_reentry": 0.0,
    "detail_qty_inspect": 0.0,
    "detail_amt_inspect": 0.0,
    "detail_qty_cut": 0.0,
    "detail_amt_cut": 0.0,
    "detail_pallets": 4,
    "qty_total": 24.0,
    "amt_total": 16341828.0
  },
  {
    "work_date": "2026-07-11",
    "brand": "3PL",
    "worker": "정준석",
    "worker_display": "정준석",
    "rows": 3,
    "hours": 2.048333,
    "basic_qty_normal": 17.0,
    "basic_amt_normal": 3737500.0,
    "basic_qty_return": 0.0,
    "basic_amt_return": 0.0,
    "basic_qty_cut": 0.0,
    "basic_amt_cut": 0.0,
    "basic_pallets": 3,
    "detail_qty_normal": 17.0,
    "detail_amt_normal": 3737500.0,
    "detail_qty_return": 0.0,
    "detail_amt_return": 0.0,
    "detail_qty_certify": 0.0,
    "detail_amt_certify": 0.0,
    "detail_qty_reentry": 0.0,
    "detail_amt_reentry": 0.0,
    "detail_qty_inspect": 0.0,
    "detail_amt_inspect": 0.0,
    "detail_qty_cut": 0.0,
    "detail_amt_cut": 0.0,
    "detail_pallets": 3,
    "qty_total": 17.0,
    "amt_total": 3737500.0
  }
]